{
  "version": "0.2",
  "language": "en",
  "dictionaryDefinitions": [
    {
      "name": "common-words",
      "path": "./dictionaries/common-words.md",
      "addWords": false
    },
    {
      "name": "professional-words",
      "path": "./dictionaries/professional-words.md",
      "addWords": false
    },
    {
      "name": "uncatagorized-words",
      "path": "./dictionaries/uncatagorized-words.md",
      "addWords": true
    }
  ],
  "ignoreRegExpList": ["Email"],
  "ignorePaths": [
    "./cspell.json",
    "auto-imports.d.ts",
    "components.d.ts",
    "pnpm-lock.yaml",
    "./package.json",
    "./package-lock.json",
    "./yarn.lock",
    "./Dockerfile",
    "./tsconfig.json",
    "./tsconfig.*",
    "vite.config.js",
    "vite.config.*",
    "webpack.config.js",
    "webpack.config.*",
    "dictionaries",
    "node_modules",
    "dist",
    "build",
    "out",
    "output",
    "public",
    "release",
    "vendor",
    "tmp",
    "temp",
    ".*",
    "*.min.*",
    "*.map",
    "*.log",
    "*.log.*",
    "*.cache",
    "*.tgz",
    "*.zip",
    "*.rar",
    "*.7z",
    "*.png",
    "*.jpg",
    "*.jpeg",
    "*.gif",
    "*.svg",
    "*.ico",
    "*.ttf",
    "*.webp",
    "*.mp3",
    "*.mp4",
    "*.avi",
    "*.gz",
    "*.tar",
    "*.exe",
    "*.dll",
    "*.obj",
    "*.o",
    "*.bin",
    "*.so",
    "*.a",
    "*.lib",
    "*.dylib",
    "*.app",
    "*.ipa",
    "*.apk",
    "*.dmg",
    "*.iso",
    "*.woff",
    "*.woff2",
    "*.ttf",
    "*.eot",
    "*.pdf",
    "*.doc",
    "*.docx",
    "*.xls",
    "*.xlsx",
    "*.ppt",
    "*.pptx",
    "*.cert",
    "*.key",
    "*.crt",
    "*.manifest",
    "*.settings",
    "*.config",
    "*.config.user",
    "*.cache",
    "*.log",
    "*.log.*"
  ],
  "dictionaries": [
    "professional-words",
    "common-words",
    "uncatagorized-words",
    "fonts",
    "npm",
    "filetypes",
    "typescript",
    "node",
    "go",
    "html",
    "css",
    "bash",
    "en_US",
    "en-gb",
    "companies",
    "softwareTerms",
    "misc"
  ],
  "minWordLength": 3
}
